{
  "id": "dpl_96UEynzJQ545bAf9ZQqiNGwdkQJN",
  "name": "frc-app",
  "url": "frc-kikepytls-mrpina-s-projects.vercel.app",
  "target": "production",
  "readyState": "READY",
  "createdAt": 1780336694181,
  "aliases": [
    "frc-app-liard.vercel.app",
    "frc-app-mrpina-s-projects.vercel.app",
    "frc-app-git-main-mrpina-s-projects.vercel.app"
  ],
  "builds": [
    {
      "id": "bld_3cdara1u7",
      "deploymentId": "dpl_96UEynzJQ545bAf9ZQqiNGwdkQJN",
      "entrypoint": ".",
      "readyState": "READY",
      "readyStateAt": 1780336694400,
      "createdAt": 1780336694400,
      "createdIn": "sfo1",
      "use": "@vercel/vc-build",
      "config": {
        "framework": "vite",
        "buildCommand": "npm run build",
        "outputDirectory": "dist",
        "nodeVersion": "24.x",
        "projectCreatedAt": 1780287666440,
        "vercelConfig": {
          "rewrites": [
            {
              "source": "/(.*)",
              "destination": "/index.html"
            }
          ]
        }
      },
      "middleware": [],
      "output": [],
      "fingerprint": null
    }
  ],
  "contextName": "mrpina-s-projects"
}
